fossil_cli/__init__.py
fossil_cli/__main__.py
fossil_cli/Branch.py
fossil_cli/Commit.py
fossil_cli/Info.py
fossil_cli/New.py
fossil_cli/utils.py
fossil_cli/Version.py
fossil_cli-4.5.2.dist-info/entry_points.txt
fossil_cli-4.5.2.dist-info/LICENSE
fossil_cli-4.5.2.dist-info/METADATA
fossil_cli-4.5.2.dist-info/WHEEL
fossil_cli-4.5.2.dist-info/RECORD
