Metadata-Version: 2.3
Name: fossil-cli
Version: 4.5.2
Summary: Fossil Cli Helper
License: MIT
Author: Lorenzo Antonio Garcia Calzadilla
Author-email: lorenzogarciacalzadilla@gmail.com
Requires-Python: >=3.13,<4.0
Classifier: Development Status :: 3 - Alpha
Classifier: Environment :: Console :: Curses
Classifier: Intended Audience :: Developers
Classifier: License :: OSI Approved :: MIT License
Classifier: Programming Language :: Python :: 3
Classifier: Programming Language :: Python :: 3.13
Classifier: Topic :: Software Development :: Version Control
Classifier: Topic :: Utilities
Requires-Dist: black (>=25.1.0,<26.0.0)
Requires-Dist: click
Requires-Dist: pyflakes (>=3.2.0,<4.0.0)
Requires-Dist: pytest-cov (>=6.0.0,<7.0.0)
Requires-Dist: questionary
Requires-Dist: semver
